amqpstorm_flask/RabbitMQ.py
amqpstorm_flask/__init__.py
amqpstorm_flask/exchange_params.py
amqpstorm_flask/queue_params.py
amqpstorm_flask-0.5.3.dist-info/licenses/LICENSE
amqpstorm_flask-0.5.3.dist-info/METADATA
amqpstorm_flask-0.5.3.dist-info/WHEEL
amqpstorm_flask-0.5.3.dist-info/top_level.txt
amqpstorm_flask-0.5.3.dist-info/RECORD
