Metadata-Version: 2.4
Name: amqpstorm-flask
Version: 0.5.3
Summary: amqpstorm library for Flask
Author-email: Inuits <developers@inuits.eu>
License:                     GNU GENERAL PUBLIC LICENSE
Project-URL: Homepage, https://github.com/inuits/amqpstorm-flask
Keywords: amqpstorm_flask,amqpstorm-flask
Classifier: License :: OSI Approved :: GNU General Public License v2 (GPLv2)
Classifier: Intended Audience :: Developers
Classifier: Programming Language :: Python :: 3.10
Classifier: Programming Language :: Python :: 3.11
License-File: LICENSE
Requires-Dist: AMQPStorm>=2.10
Requires-Dist: Flask>=2.3
Requires-Dist: retry>=0.9
Requires-Dist: apscheduler>=3.11
Dynamic: license-file
